did_had/__init__.py
did_had/core.py
did_had/py.typed
did_had/utils.py
did_had-0.2.0.dist-info/licenses/LICENSE
did_had-0.2.0.dist-info/METADATA
did_had-0.2.0.dist-info/WHEEL
did_had-0.2.0.dist-info/top_level.txt
did_had-0.2.0.dist-info/RECORD
