Metadata-Version: 2.4
Name: did-had
Version: 0.2.0
Summary: Difference-in-Differences with Heterogeneous Adoption Design (HAD) estimator
Author-email: Anzony Quispe <anzonyquispe@gmail.com>
Maintainer-email: Anzony Quispe <anzonyquispe@gmail.com>
License: MIT
Project-URL: Homepage, https://github.com/anzonyquispe/did-had
Project-URL: Documentation, https://github.com/anzonyquispe/did-had#readme
Project-URL: Repository, https://github.com/anzonyquispe/did-had.git
Project-URL: Issues, https://github.com/anzonyquispe/did-had/issues
Keywords: difference-in-differences,causal inference,econometrics,heterogeneous treatment effects,panel data,did,had,nprobust,local polynomial regression
Classifier: Development Status :: 4 - Beta
Classifier: Intended Audience :: Science/Research
Classifier: License :: OSI Approved :: MIT License
Classifier: Operating System :: OS Independent
Classifier: Programming Language :: Python :: 3
Classifier: Programming Language :: Python :: 3.8
Classifier: Programming Language :: Python :: 3.9
Classifier: Programming Language :: Python :: 3.10
Classifier: Programming Language :: Python :: 3.11
Classifier: Programming Language :: Python :: 3.12
Classifier: Topic :: Scientific/Engineering :: Mathematics
Classifier: Topic :: Scientific/Engineering :: Information Analysis
Requires-Python: >=3.8
License-File: LICENSE
Requires-Dist: numpy>=1.20.0
Requires-Dist: pandas>=1.3.0
Requires-Dist: scipy>=1.7.0
Requires-Dist: nprobust>=0.5.0
Provides-Extra: plot
Requires-Dist: matplotlib>=3.4.0; extra == "plot"
Requires-Dist: seaborn>=0.11.0; extra == "plot"
Provides-Extra: dev
Requires-Dist: pytest>=7.0.0; extra == "dev"
Requires-Dist: pytest-cov>=4.0.0; extra == "dev"
Requires-Dist: black>=23.0.0; extra == "dev"
Requires-Dist: isort>=5.12.0; extra == "dev"
Requires-Dist: mypy>=1.0.0; extra == "dev"
Provides-Extra: all
Requires-Dist: matplotlib>=3.4.0; extra == "all"
Requires-Dist: pytest>=7.0.0; extra == "all"
Requires-Dist: pytest-cov>=4.0.0; extra == "all"
Dynamic: license-file
